{
	"server_title" : "MainServerConsumer",
	"server_sub_title" : "MainServerConsumer",
	"main_registered_key": "main_server_consumer",
	"high_priority_count" : 3,
	"normal_priority_count" : 3,
	"low_priority_count" : 5,
	"write_console_log" : 3,
	"write_file_log" : 0,
	"console_windows": false,

	"use_redis_tls": false,
	"use_redis": true,
	"redis_host": "127.0.0.1",
	"redis_port": 6379,
	"redis_ttl_sec": 600,
	"redis_db_global_message_index": 0,
	"redis_db_user_status_index": 1,
	"global_message_key": "send_global_message",

	"use_ssl": false,
	"win_ca_cert" : "",
	"linux_ca_cert" : "",
	"ca_cert" : "",

	"rabbit_mq_host": "localhost",
	"rabbit_mq_port": 5672,
	"rabbit_mq_user_name": "guest",
	"rabbit_mq_password": "guest",

	"consume_queue_name": "message_broadcast_queue",
	
	"empty": ""
}